<annotation>
  <folder>input</folder>
  <filename>407.jpg</filename>
  <path>/home/gaurav/YOLO/OpenLabeling/main/input/407.jpg</path>
  <source>
    <database>Unknown</database>
  </source>
  <size>
    <width>1024</width>
    <height>1024</height>
    <depth>3</depth>
  </size>
  <segmented>0</segmented>
  <object>
    <name>power_drill</name>
    <pose>Unspecified</pose>
    <truncated>0</truncated>
    <difficult>0</difficult>
    <bndbox>
      <xmin>583</xmin>
      <ymin>437</ymin>
      <xmax>715</xmax>
      <ymax>553</ymax>
    </bndbox>
  </object>
</annotation>
